blimb/__init__.py
bilmb-0.1.0.dist-info/METADATA
bilmb-0.1.0.dist-info/WHEEL
bilmb-0.1.0.dist-info/top_level.txt
bilmb-0.1.0.dist-info/RECORD
