Metadata-Version: 2.4
Name: bilmb
Version: 0.1.0
Summary: A minimal library with a special message for Dilda
Author-email: Your Name <you@example.com>
Requires-Python: >=3.7
